[
	{
		"name" : "Inputswitch Joystick",
		"file" : "inputswitchjoy",
		"extension" : "ipf",
		"fileVersion" : "v1.2.0",
		"releaseTag" : "120",
		"unicode" : "⛄",
		"description" : "Modified version of axjv's input switcher. Now you can toggle between mouse, keyboard and CONTROLLER mode.",
		"tags" : [
			"input",
			"keyboard",
			"mouse",
			"controller",
			"joystick"
			]
	},
	{
		"name" : "FPS Savior v2",
		"file" : "fpssavior",
		"extension" : "ipf",
		"fileVersion" : "v2.1.0",
		"releaseTag" : "fpssavior",
		"unicode" : "⛄",
		"description" : "Updated version of fpssavior",
		"tags" : [
			"fps",
			"graphic",
			"savior"
			]
	},
	{
		"name" : "Auto Pamoka (Alert)",
		"file" : "autopamoka",
		"extension" : "ipf",
		"fileVersion" : "v1.2.2",
		"releaseTag" : "autopamoka",
		"unicode" : "⛄",
		"description" : "Auto enable pamoka(unnecessary now) and Alert function! /autopamoka",
		"tags" : [
			"pamoka",
			"exporb",
			"alert"
			]
	},
	{
		"name" : "Alchemist Calculator",
		"file" : "alchcalc",
		"extension" : "ipf",
		"fileVersion" : "v1.0.1",
		"releaseTag" : "alchcalc",
		"unicode" : "⛄",
		"description" : "Simple calculator for lazy merchants.",
		"tags" : [
			"alchemist",
			"alch",
			"calculator"
			]
	},
	{
		"name" : "Enchant Search",
		"file" : "enchantsearch",
		"extension" : "ipf",
		"fileVersion" : "v0.1.0",
		"releaseTag" : "enchantsearch",
		"unicode" : "⛄",
		"description" : "Let you search items with enchant.",
		"tags" : [
			"enchant",
			"search",
			"market"
			]
	},
	{
		"name" : "Assister Plus",
		"file" : "assisterplus",
		"extension" : "ipf",
		"fileVersion" : "v1.0.0",
		"releaseTag" : "assisterplus",
		"unicode" : "⛄",
		"description" : "Adds extra functions to the assisters UI.",
		"tags" : [
			"assister",
			"assisters",
			"assistersplus",
			"ui"
			]
	}
]

